udene_sdk/__init__.py
udene_sdk/client.py
udene_sdk-1.0.0.dist-info/METADATA
udene_sdk-1.0.0.dist-info/WHEEL
udene_sdk-1.0.0.dist-info/top_level.txt
udene_sdk-1.0.0.dist-info/RECORD
