Metadata-Version: 2.4
Name: udene-sdk
Version: 1.0.0
Summary: Python SDK for Udene API
Home-page: https://github.com/udene/udene-python
Author: Udene Team
Author-email: support@udene.com
Keywords: udene,sdk,api
Classifier: Programming Language :: Python :: 3
Classifier: License :: OSI Approved :: MIT License
Classifier: Operating System :: OS Independent
Requires-Python: >=3.6
Requires-Dist: requests>=2.25.0
Dynamic: author
Dynamic: author-email
Dynamic: classifier
Dynamic: home-page
Dynamic: keywords
Dynamic: requires-dist
Dynamic: requires-python
Dynamic: summary
